{
  "termo": "Deputado Joaquim Lira",
  "total": 5,
  "itens": [
    {
      "titulo": "deputado Joaquim Lira",
      "url": "https://www.alepe.pe.gov.br/parlamentar/joaquim-lira/",
      "trecho": "Empresário e advogado, com formação em Direito pela Faculdade Aeso Barros Melo, de Olinda, o parlamentar é avaliado pelo perfil conciliador, dotado de uma visão ...",
      "canal": "Site",
      "sentimento": "neutro",
      "tags": []
    },
    {
      "titulo": "Joaquim Lira (@joaquimlirape) • Instagram photos and videos",
      "url": "https://www.instagram.com/joaquimlirape/",
      "trecho": "27K followers · 3.6K+ following · 3352 posts · @joaquimlirape: “ Deputado Estadual por Pernambuco Líder da Frente Parlamentar de Saneamento Advogado e ...",
      "canal": "Instagram",
      "sentimento": "neutro",
      "tags": []
    },
    {
      "titulo": "Joaquim Lira – Wikipédia, a enciclopédia livre",
      "url": "https://pt.wikipedia.org/wiki/Joaquim_Lira",
      "trecho": "Joaquim Elias Carneiro de Lira (Recife, 24 de fevereiro de 1984), é um advogado e político brasileiro. É deputado estadual de Pernambuco pelo PV.",
      "canal": "Site",
      "sentimento": "neutro",
      "tags": []
    },
    {
      "titulo": "Eleições 2022: Joaquim Lira - PV | Ficha do candidato | Folha",
      "url": "https://www1.folha.uol.com.br/poder/eleicoes/candidatos/2022/pe/deputado-estadual/joaquim-lira-170001608973.shtml",
      "trecho": "Confira o perfil de Joaquim Lira, candidato(a) a deputado estadual nas eleições de 2022 na Folha.",
      "canal": "Site",
      "sentimento": "neutro",
      "tags": []
    },
    {
      "titulo": "Deputado Federal LIRA MAIA - Portal da Câmara dos Deputados",
      "url": "https://www.camara.leg.br/deputados/141462",
      "trecho": "LIRA MAIA. Não está em exercício · Nome Civil: JOAQUIM DE LIRA MAIA · Partido: DEM - PA · Data de Nascimento: 01/09/1952 · Naturalidade: Santarém - PA · Biografia ...",
      "canal": "Site",
      "sentimento": "neutro",
      "tags": []
    }
  ]
}